echostream_botocore/__init__.py
echostream_botocore-0.1.0.dist-info/LICENSE
echostream_botocore-0.1.0.dist-info/METADATA
echostream_botocore-0.1.0.dist-info/WHEEL
echostream_botocore-0.1.0.dist-info/top_level.txt
echostream_botocore-0.1.0.dist-info/RECORD
