Metadata-Version: 2.1
Name: echostream-botocore
Version: 0.1.0
Summary: Provides a botocore.session.Session implementation for accessing EchoStream Tenant resources
Author: EchoStream
Author-email: pypi@echo.stream
Requires-Python: >=3.12
License-File: LICENSE
Requires-Dist: botocore
Requires-Dist: gql[requests] ==3.5.0
Requires-Dist: pycognito ==2024.5.1
